drb_impl_s3/__init__.py
drb_impl_s3/_version.py
drb_impl_s3/cortex.yml
drb_impl_s3/drb_impl_s3.py
drb_impl_s3/s3_node_factory.py
drb_impl_s3/utility.py
drb_impl_s3-1.0.0.data/data/requirements.txt
drb_impl_s3-1.0.0.dist-info/METADATA
drb_impl_s3-1.0.0.dist-info/WHEEL
drb_impl_s3-1.0.0.dist-info/entry_points.txt
drb_impl_s3-1.0.0.dist-info/top_level.txt
drb_impl_s3-1.0.0.dist-info/RECORD
