Metadata-Version: 2.1
Name: drb-impl-s3
Version: 1.0.0
Summary: DRB aws3 implementation
Home-page: https://gitlab.com/drb-python/impl/aws3
Author: GAEL Systems
Author-email: drb-python@gael.fr
License: UNKNOWN
Project-URL: Documentation, https://drb-python.gitlab.io/impl/aws3/
Project-URL: Source, https://gitlab.com/drb-python/impl/aws3
Platform: UNKNOWN
Classifier: Programming Language :: Python :: 3.8
Classifier: License :: OSI Approved :: Apache Software License
Classifier: Operating System :: OS Independent
Requires-Python: >=3.8
Requires-Dist: drb (<1.1.0,>=1.0.1)
Requires-Dist: boto3 (==1.21.40)
Requires-Dist: botocore (==1.24.41)
Requires-Dist: drb-impl-http (==1.0.5)
Requires-Dist: moto (==3.1.4)
Requires-Dist: versioneer (~=0.22)
Requires-Dist: setuptools (~=58.5.3)
Requires-Dist: requests (~=2.27.1)
